pyodoo_connect/__init__.py
pyodoo_connect/odoo.py
pyodoo_connect/tools.py
tests/__init__.py
tests/test_odoo.py
pyodoo_connect-0.2.0.dist-info/LICENSE
pyodoo_connect-0.2.0.dist-info/METADATA
pyodoo_connect-0.2.0.dist-info/WHEEL
pyodoo_connect-0.2.0.dist-info/top_level.txt
pyodoo_connect-0.2.0.dist-info/RECORD
