Metadata-Version: 2.1
Name: pyodoo_connect
Version: 0.2.0
Summary: A Python package to interact with Odoo via JSON-RPC.
Home-page: https://github.com/fasilwdr/pyodoo_connector
Author: Fasil
Author-email: Fasil <fasilwdr@hotmail.com>
License: MIT License
Classifier: Development Status :: 3 - Alpha
Classifier: Intended Audience :: Developers
Classifier: License :: OSI Approved :: MIT License
Classifier: Programming Language :: Python :: 3
Classifier: Programming Language :: Python :: 3.6
Classifier: Programming Language :: Python :: 3.7
Classifier: Programming Language :: Python :: 3.8
Classifier: Programming Language :: Python :: 3.9
Classifier: Programming Language :: Python :: 3.10
Requires-Python: >=3.6
License-File: LICENSE
Requires-Dist: httpx>=0.24.0
